mongodb_connect/__init__.py
mongodb_connect/mongo_crud.py
mongodb_connect_avasaralashivani-0.1.0.dist-info/METADATA
mongodb_connect_avasaralashivani-0.1.0.dist-info/WHEEL
mongodb_connect_avasaralashivani-0.1.0.dist-info/top_level.txt
mongodb_connect_avasaralashivani-0.1.0.dist-info/RECORD
