Metadata-Version: 2.1
Name: mongodb_connect_avasaralashivani
Version: 0.1.0
Home-page: https://github.com/ShivaniAvasarala/PackageTest.git
Author: ShivaniAvasarala
Author-email: avasaralashivani@gmail.com
Classifier: Programming Language :: Python :: 3.7
Classifier: Programming Language :: Python :: 3.8
Classifier: Programming Language :: Python :: 3.9
Classifier: Operating System :: OS Independent
Requires-Python: >=3.7
Provides-Extra: testing
Requires-Dist: pytest>=7.1.3; extra == "testing"
Requires-Dist: mypy>=0.971; extra == "testing"
Requires-Dist: flake8>=3.9.2; extra == "testing"
Requires-Dist: tox>=3.25.1; extra == "testing"
Requires-Dist: black>=22.8.0; extra == "testing"
